beaufort_scale/__init__.py
beaufort_scale/beaufort_scale.py
beaufort_scale-1.0.2.dist-info/LICENSE.txt
beaufort_scale-1.0.2.dist-info/METADATA
beaufort_scale-1.0.2.dist-info/WHEEL
beaufort_scale-1.0.2.dist-info/top_level.txt
beaufort_scale-1.0.2.dist-info/RECORD
