Metadata-Version: 2.1
Name: beaufort_scale
Version: 1.0.2
Home-page: https://github.com/BrunoASNascimento/beaufort-scale
Author: Bruno Nascimento
Author-email: bruno_freddy@hotmail.com
License: MIT
Project-URL: Código fonte, https://github.com/BrunoASNascimento/beaufort-scale
Project-URL: Download, https://github.com/BrunoASNascimento/beaufort-scale/archive/master.zip
Keywords: conversor,wind,speed,beaufort
Classifier: Development Status :: 5 - Production/Stable
Classifier: Intended Audience :: Developers
Classifier: License :: OSI Approved :: MIT License
Classifier: Natural Language :: Portuguese (Brazilian)
Classifier: Operating System :: OS Independent
Classifier: Topic :: Software Development :: Internationalization
Classifier: Topic :: Scientific/Engineering :: Physics
Requires-Python: >=3.4
License-File: LICENSE.txt
